verilog/ram.v
`timescale 1ns/1ps

module ram (
    input  wire       clk,
    input  wire       we,
    input  wire [3:0] addr,
    input  wire [7:0] din,
    output reg  [7:0] dout
);

reg [7:0] mem [0:15];
integer i;

initial begin
    for (i = 0; i < 16; i = i + 1)
        mem[i] = 8'h00;
end

always @(posedge clk) begin
    if (we)
        mem[addr] <= din;
    dout <= mem[addr];
end

endmodule


module tb;

reg clk;
reg we;
reg [3:0] addr;
reg [7:0] din;
wire [7:0] dout;

ram uut (
    .clk(clk),
    .we(we),
    .addr(addr),
    .din(din),
    .dout(dout)
);

// 时钟：10ns 周期
initial begin
    clk = 0;
    forever #5 clk = ~clk;
end

// 波形和测试流程
initial begin
    $dumpfile("ram.vcd");
    $dumpvars(0, tb);

    // 也可以加监视，方便看变化
    $monitor("t=%0t clk=%b we=%b addr=%0d din=%h dout=%h",
             $time, clk, we, addr, din, dout);

    we   = 0;
    addr = 0;
    din  = 0;

    // 在下降沿之后再改输入，避免和 posedge 打架
    @(negedge clk);
    we   = 1;
    addr = 4'h3;
    din  = 8'hAA;

    @(negedge clk);
    addr = 4'h5;
    din  = 8'h55;

    @(negedge clk);
    we   = 0;
    addr = 4'h3;

    @(negedge clk);
    addr = 4'h5;

    @(negedge clk);
    $finish;
end

endmodule

verilog/ram.vcd
$date
	Sat Apr 25 18:19:17 2026
$end
$version
	Icarus Verilog
$end
$timescale
	1ps
$end
$scope module tb $end
$var wire 8 ! dout [7:0] $end
$var reg 4 " addr [3:0] $end
$var reg 1 # clk $end
$var reg 8 $ din [7:0] $end
$var reg 1 % we $end
$scope module uut $end
$var wire 4 & addr [3:0] $end
$var wire 1 # clk $end
$var wire 8 ' din [7:0] $end
$var wire 1 % we $end
$var reg 8 ( dout [7:0] $end
$var integer 32 ) i [31:0] $end
$upscope $end
$upscope $end
$enddefinitions $end
$comment Show the parameter values. $end
$dumpall
$end
#0
$dumpvars
b10000 )
bx (
b0 '
b0 &
0%
b0 $
0#
b0 "
bx !
$end
#5000
b0 !
b0 (
1#
#10000
b10101010 $
b10101010 '
b11 "
b11 &
1%
0#
#15000
1#
#20000
b1010101 $
b1010101 '
b101 "
b101 &
0#
#25000
1#
#30000
b11 "
b11 &
0%
0#
#35000
b10101010 !
b10101010 (
1#
#40000
b101 "
b101 &
0#
#45000
b1010101 !
b1010101 (
1#
